ae/db_core.py
ae_db_core-0.3.16.dist-info/LICENSE.md
ae_db_core-0.3.16.dist-info/METADATA
ae_db_core-0.3.16.dist-info/WHEEL
ae_db_core-0.3.16.dist-info/top_level.txt
ae_db_core-0.3.16.dist-info/zip-safe
ae_db_core-0.3.16.dist-info/RECORD
